{"wmsURL": "http://earthserver.pml.ac.uk/thredds/wms/CEFAS/resoutcut.nc?", "wcsURL": "http://earthserver.pml.ac.uk/thredds/wcs/CEFAS/resoutcut.nc?", "serverName": "cefas", "options": {"providerShortTag": "Cefas"}, "server": {"EwE-North_Sea_HTL": [{"Name": "Cod__adult_", "Title": "Cod__adult_", "Abstract": "Cod__adult_", "tags": {"Confidence": "Low", "niceName": "Adult Cod", "region": "N. Atlantic", "interval": "daily", "MSFD": ["Foodwebs", "Fisheries"], "Ecosystem_Element": "Fish"}, "LastDate": "2009-11-13", "FirstDate": "1991-02-02", "EX_GeographicBoundingBox": {"WestBoundLongitude": "-6.0", "NorthBoundLatitude": "61.66666793823242", "EastBoundLongitude": "9.833175659179688", "SouthBoundLatitude": "51.0001106262207"}}, {"Name": "Herbivorous_and_Omnivorous_zooplankton__copepods_", "Title": "Herbivorous_and_Omnivorous_zooplankton__copepods_", "Abstract": "Herbivorous_and_Omnivorous_zooplankton__copepods_", "tags": {"Confidence": "Medium", "niceName": "Zooplankton", "region": "N. Atlantic", "interval": "daily", "MSFD": ["Eutrophication", "Biodiversity", "Foodwebs"], "Ecosystem_Element": "Zooplankton"}, "LastDate": "2009-11-13", "FirstDate": "1991-02-02", "EX_GeographicBoundingBox": {"WestBoundLongitude": "-6.0", "NorthBoundLatitude": "61.66666793823242", "EastBoundLongitude": "9.833175659179688", "SouthBoundLatitude": "51.0001106262207"}}, {"Name": "Herring__adult_", "Title": "Herring__adult_", "Abstract": "Herring__adult_", "tags": {"Confidence": "Medium", "niceName": "Adult herring", "region": "N. Atlantic", "interval": "daily", "MSFD": ["Foodwebs", "Fisheries"], "Ecosystem_Element": "Fish"}, "LastDate": "2009-11-13", "FirstDate": "1991-02-02", "EX_GeographicBoundingBox": {"WestBoundLongitude": "-6.0", "NorthBoundLatitude": "61.66666793823242", "EastBoundLongitude": "9.833175659179688", "SouthBoundLatitude": "51.0001106262207"}}, {"Name": "Herring__juvenile_0__1_", "Title": "Herring__juvenile_0__1_", "Abstract": "Herring__juvenile_0__1_", "tags": {"Confidence": "Low", "niceName": "Juvenile herring", "region": "N. Atlantic", "interval": "daily", "MSFD": ["Foodwebs", "Fisheries"], "Ecosystem_Element": "Fish"}, "LastDate": "2009-11-13", "FirstDate": "1991-02-02", "EX_GeographicBoundingBox": {"WestBoundLongitude": "-6.0", "NorthBoundLatitude": "61.66666793823242", "EastBoundLongitude": "9.833175659179688", "SouthBoundLatitude": "51.0001106262207"}}, {"Name": "Juvenile_Cod_0_2__0_40cm_", "Title": "Juvenile_Cod_0_2__0_40cm_", "Abstract": "Juvenile_Cod_0_2__0_40cm_", "tags": {"Confidence": "Low", "niceName": "Juvenile cod", "region": "N. Atlantic", "interval": "daily", "MSFD": ["Foodwebs", "Fisheries"], "Ecosystem_Element": "Fish"}, "LastDate": "2009-11-13", "FirstDate": "1991-02-02", "EX_GeographicBoundingBox": {"WestBoundLongitude": "-6.0", "NorthBoundLatitude": "61.66666793823242", "EastBoundLongitude": "9.833175659179688", "SouthBoundLatitude": "51.0001106262207"}}, {"Name": "Phytoplankton", "Title": "Phytoplankton", "Abstract": "Phytoplankton", "tags": {"Confidence": "Medium", "niceName": "Phytoplankton biomass", "region": "N. Atlantic", "interval": "daily", "MSFD": ["Eutrophication", "Biodiversity", "Foodwebs"], "Ecosystem_Element": "Phytoplankton"}, "LastDate": "2009-11-13", "FirstDate": "1991-02-02", "EX_GeographicBoundingBox": {"WestBoundLongitude": "-6.0", "NorthBoundLatitude": "61.66666793823242", "EastBoundLongitude": "9.833175659179688", "SouthBoundLatitude": "51.0001106262207"}}, {"Name": "Plaice", "Title": "Plaice", "Abstract": "Plaice", "tags": {"Confidence": "Low", "niceName": "Plaice", "region": "N. Atlantic", "interval": "daily", "MSFD": ["Foodwebs", "Fisheries"], "Ecosystem_Element": "Fish"}, "LastDate": "2009-11-13", "FirstDate": "1991-02-02", "EX_GeographicBoundingBox": {"WestBoundLongitude": "-6.0", "NorthBoundLatitude": "61.66666793823242", "EastBoundLongitude": "9.833175659179688", "SouthBoundLatitude": "51.0001106262207"}}, {"Name": "Sandeels", "Title": "Sandeels", "Abstract": "Sandeels", "tags": {"Confidence": "Low", "niceName": "Sandeels", "region": "N. Atlantic", "interval": "daily", "MSFD": ["Foodwebs", "Fisheries"], "Ecosystem_Element": "Fish"}, "LastDate": "2009-11-13", "FirstDate": "1991-02-02", "EX_GeographicBoundingBox": {"WestBoundLongitude": "-6.0", "NorthBoundLatitude": "61.66666793823242", "EastBoundLongitude": "9.833175659179688", "SouthBoundLatitude": "51.0001106262207"}}, {"Name": "Seabirds", "Title": "Seabirds", "Abstract": "Seabirds", "tags": {"Confidence": "Low", "niceName": "Seabirds", "region": "N. Atlantic", "interval": "daily", "MSFD": ["Foodwebs", "Fisheries"], "Ecosystem_Element": "Fish"}, "LastDate": "2009-11-13", "FirstDate": "1991-02-02", "EX_GeographicBoundingBox": {"WestBoundLongitude": "-6.0", "NorthBoundLatitude": "61.66666793823242", "EastBoundLongitude": "9.833175659179688", "SouthBoundLatitude": "51.0001106262207"}}]}}